{
  "id": 14,
  "theme": "History",
  "difficulty": "easy",
  "grid_size": 15,
  "clues": {
    "across": [
      {
        "number": 5,
        "clue": "House pet",
        "answer": "CAT"
      },
      {
        "number": 15,
        "clue": "Colorful bloom",
        "answer": "FLOWER"
      },
      {
        "number": 8,
        "clue": "Grass color",
        "answer": "GREEN"
      },
      {
        "number": 15,
        "clue": "Green ground cover",
        "answer": "GRASS"
      },
      {
        "number": 1,
        "clue": "Cooking pot",
        "answer": "PAN"
      },
      {
        "number": 12,
        "clue": "Sunny weather",
        "answer": "CLEAR"
      },
      {
        "number": 12,
        "clue": "Rain drops",
        "answer": "WATER"
      }
    ],
    "down": [
      {
        "number": 3,
        "clue": "Sleep place",
        "answer": "BED"
      },
      {
        "number": 2,
        "clue": "Mail carrier",
        "answer": "POSTMAN"
      },
      {
        "number": 3,
        "clue": "Sitting furniture",
        "answer": "CHAIR"
      },
      {
        "number": 1,
        "clue": "Happy dance",
        "answer": "JIG"
      },
      {
        "number": 4,
        "clue": "Light source",
        "answer": "LAMP"
      },
      {
        "number": 4,
        "clue": "Time teller",
        "answer": "CLOCK"
      }
    ]
  },
  "grid_image": "books/active_production/Large_Print_Crossword_Masters/volume_3/puzzles/puzzle_014.png",
  "created_at": "2025-06-24T15:49:31.451141"
}